{
  "data": [
    {
      "id": 1,
      "name": "John",
      "age": 30
    },
    {
      "id": 2,
      "name": "Manish",
      "age": 30
    },
    {
      "id": 3,
      "name": "Jay",
      "age": 30
    },
    {
      "id": 3,
      "name": "Ronak",
      "age": 30
    },
    {
      "id": 3,
      "name": "Kamlesh",
      "age": 30
    },
    {
      "id": 3,
      "name": "Rajes",
      "age": 30
    },
    {
      "id": 3,
      "name": "Mohan",
      "age": 30
    },
    {
      "id": 3,
      "name": "Patil",
      "age": 30
    }
  ]
}
